{
  "$defs": {
    "CapabilityDescriptor": {
      "properties": {
        "description": {
          "default": null,
          "type": [
            "string",
            "null"
          ]
        },
        "id": {
          "type": "string"
        },
        "input_schema": {
          "default": null
        },
        "output_schema": {
          "default": null
        },
        "side_effects": {
          "default": [],
          "items": {
            "type": "string"
          },
          "type": "array"
        },
        "streaming": {
          "default": false,
          "type": "boolean"
        },
        "version": {
          "type": "string"
        }
      },
      "required": [
        "id",
        "version"
      ],
      "type": "object"
    },
    "ComponentBoundaryClaims": {
      "properties": {
        "filesystem_isolation": {
          "type": "boolean"
        },
        "network_isolation": {
          "type": "boolean"
        },
        "no_code_execution": {
          "type": "boolean"
        },
        "process_failure_isolation": {
          "type": "boolean"
        },
        "remote_identity": {
          "type": "boolean"
        },
        "resource_limits_enforced": {
          "type": "boolean"
        },
        "revocation_enforced": {
          "type": "boolean"
        },
        "tenancy_isolation": {
          "type": "boolean"
        }
      },
      "required": [
        "filesystem_isolation",
        "network_isolation",
        "no_code_execution",
        "process_failure_isolation",
        "remote_identity",
        "resource_limits_enforced",
        "revocation_enforced",
        "tenancy_isolation"
      ],
      "type": "object"
    },
    "ComponentClaimStatus": {
      "enum": [
        "declared",
        "legacy_adapted",
        "foreign_capsule"
      ],
      "type": "string"
    },
    "ComponentTrustClass": {
      "enum": [
        "sandboxed_component",
        "isolated_process",
        "remote_boundary",
        "trusted_native",
        "static_resource",
        "foreign_capsule"
      ],
      "type": "string"
    },
    "Errors": {
      "items": {
        "$schema": "https://json-schema.org/draft/2020-12/schema",
        "properties": {
          "code": {
            "type": "string"
          },
          "details": true,
          "message": {
            "type": "string"
          }
        },
        "required": [
          "code",
          "details",
          "message"
        ],
        "title": "ErrorShape",
        "type": "object"
      },
      "type": "array"
    },
    "Params": {
      "$schema": "https://json-schema.org/draft/2020-12/schema",
      "title": "EmptyParams",
      "type": "object"
    },
    "Result": {
      "items": {
        "$schema": "https://json-schema.org/draft/2020-12/schema",
        "properties": {
          "descriptor": {
            "$ref": "#/$defs/CapabilityDescriptor"
          },
          "provider_behavior_digest": {
            "default": "",
            "type": "string"
          },
          "provider_claim_status": {
            "allOf": [
              {
                "$ref": "#/$defs/ComponentClaimStatus"
              }
            ],
            "default": "foreign_capsule"
          },
          "provider_component_digest": {
            "default": "",
            "type": "string"
          },
          "provider_component_id": {
            "default": "",
            "type": "string"
          },
          "provider_enforced_boundaries": {
            "allOf": [
              {
                "$ref": "#/$defs/ComponentBoundaryClaims"
              }
            ],
            "default": {
              "filesystem_isolation": false,
              "network_isolation": false,
              "no_code_execution": false,
              "process_failure_isolation": false,
              "remote_identity": false,
              "resource_limits_enforced": false,
              "revocation_enforced": false,
              "tenancy_isolation": false
            }
          },
          "provider_package_id": {
            "type": "string"
          },
          "provider_trust_class": {
            "allOf": [
              {
                "$ref": "#/$defs/ComponentTrustClass"
              }
            ],
            "default": "foreign_capsule"
          }
        },
        "required": [
          "descriptor",
          "provider_package_id"
        ],
        "title": "RegisteredCapability",
        "type": "object"
      },
      "type": "array"
    }
  },
  "$id": "https://yggdrasil.dev/spec/v1/methods/kernel.v1.capability.discover.schema.json",
  "$schema": "https://json-schema.org/draft/2020-12/schema",
  "additionalProperties": false,
  "description": "Yggdrasil public kernel method kernel.v1.capability.discover.",
  "properties": {
    "errors": {
      "$ref": "#/$defs/Errors"
    },
    "method": {
      "const": "kernel.v1.capability.discover"
    },
    "params": {
      "$ref": "#/$defs/Params"
    },
    "result": {
      "$ref": "#/$defs/Result"
    }
  },
  "required": [
    "method",
    "params"
  ],
  "title": "kernel.v1.capability.discover",
  "type": "object",
  "x-yggdrasil-contract": {
    "aliases": [],
    "canonical_id": "kernel.v1.capability.discover",
    "implementation_status": "implemented",
    "introduced_in": "kernel.v1@0.1.0",
    "maturity": "experimental",
    "owner_layer": "substrate",
    "request_adapter": "identity",
    "request_schema": "https://yggdrasil.dev/spec/v1/methods/kernel.v1.capability.discover.schema.json#/$defs/Params",
    "response_adapter": "identity",
    "response_schema": "https://yggdrasil.dev/spec/v1/methods/kernel.v1.capability.discover.schema.json#/$defs/Result",
    "streaming": false
  }
}
